README.md
setup.cfg
setup.py
dtsb/Binomialdistribution.py
dtsb/Gaussiandistribution.py
dtsb/Generaldistribution.py
dtsb/__init__.py
dtsb.egg-info/PKG-INFO
dtsb.egg-info/SOURCES.txt
dtsb.egg-info/dependency_links.txt
dtsb.egg-info/not-zip-safe
dtsb.egg-info/top_level.txt