Metadata-Version: 1.0
Name: dtsb
Version: 0.1
Summary: Gaussian distributions
Home-page: UNKNOWN
Author: Sunidhi Brajesh
Author-email: sunidhi.trisha185@gmail.com
License: UNKNOWN
Platform: UNKNOWN
